shii/__init__.py
shii/src/__init__.py
shii/src/study.py
shii_study-1.1.4.dist-info/METADATA
shii_study-1.1.4.dist-info/WHEEL
shii_study-1.1.4.dist-info/top_level.txt
shii_study-1.1.4.dist-info/RECORD
