Metadata-Version: 2.1
Name: shii_study
Version: 1.1.4
Summary: PYPI tutorial package creation written by Boran
Home-page: https://github.com/boranloves/shii
Author: boran
Author-email: boran <boran@shii.me>
Project-URL: Homepage, https://github.com/boranloves/shii
Project-URL: Issues, https://github.com/boranloves/shii
Classifier: Programming Language :: Python :: 3
Classifier: License :: OSI Approved :: MIT License
Classifier: Operating System :: OS Independent
Requires-Python: >=3.8
